{
    "objectId": "ac5dba16-117b-4635-855c-5e4e8b3b1dde",
    "creationDate": 1549895183689,
    "lastUpdate": 1549895183689,
    "uri": "https://sportello.comune.trento.it/modulistica/moduli/DOMANDA-DI-ACCESSO-CONSULTAZIONE-ATTI-IN-MATERIA-EDILIZIA_vSTU3",
    "eserviceId": null,
    "profileTypes": [],
    "model": {
        "context": {},
        "blocks": [
          {
              "id": "block1",
              "type": "BLOCK",
              "name": {
                  "it": "Caricamento dati del richiedente"
              },
              "xpath": "(//*[contains(@class, 'simpatico-block')])[1]",
              "tags": [],
              "fields": [
                  "AventeTitolo_CodiceFiscale"
              ],
              "blocks": [],
              "dependencies": [],
              "condition": null,
              "completed": "context['AventeTitolo_CodiceFiscale'] != null && context['AventeTitolo_CodiceFiscale'] != ''",
              "annotations": [],
              "description": {
                  "it": "Una volta effettuato l’accesso con la carta dei servizi o con SPID, premere l'icona nera a forma di omino oppure digitare il proprio codice fiscale nel campo apposito; quindi premere il pulsante <i>“Carica dati anagrafici”</i> per recuperare automaticamente le informazioni anagrafiche.<br><br>Premere sempre il pulsante <i>“SUCCESSIVO”</i> per proseguire la compilazione."
              },
              "concepts": null
          },
          {
              "id": "block2",
              "type": "BLOCK",
              "name": {
                  "it": "Anagrafica del richiedente"
              },
              "xpath": "(//*[contains(@class, 'simpatico-block')])[2]",
              "tags": [],
              "fields": [
                  "AventeTitolo_CodiceFiscale"
              ],
              "blocks": [],
              "dependencies": [
                "block1"
              ],
              "condition": "context['AventeTitolo_CodiceFiscale'] != null && context['AventeTitolo_CodiceFiscale'] != ''",
              "completed": null,
              "annotations": [],
              "description": {
                  "it": "Verificare i dati caricati automaticamente e inserire eventuali dati mancanti.<br><b>ATTENZIONE! I campi evidenziati in arancione sono obbligatori.</b>"
              },
              "concepts": null
          },
          {
              "id": "block3",
              "type": "BLOCK",
              "name": {
                  "it": "Dati di residenza del richiedente"
              },
              "xpath": "(//*[contains(@class, 'simpatico-block')])[3]",
              "tags": [],
              "fields": [],
              "blocks": [],
              "dependencies": [
                "block2"
              ],
              "condition": null,
              "completed": null,
              "annotations": [],
              "description": {
                  "it": "Sono qui riportate le informazioni relative alla residenza del richiedente, in caso di informazioni mancanti tornare al blocco iniziale e premere nuovamente <i>“Carica dati anagrafici”</i>."
              },
              "concepts": null
          },
            {
                "id": "block4",
                "type": "BLOCK",
                "name": {
                    "it": "Ruolo del richiedente"
                },
                "xpath": "(//*[contains(@class, 'simpatico-block')])[4]",
                "tags": [],
                "fields": [
                    "Tipo_richiedente1",
                    "Tipo_richiedente2",
                    "Tipo_richiedente3",
                    "Tipo_richiedente4",
                    "Tipo_richiedente5",
                    "Tipo_richiedente6"
                ],
                "blocks": [],
                "dependencies": [
                    "block3"
                ],
                "condition": null,
                "completed": "context['Tipo_richiedente1'] == '1' || context['Tipo_richiedente2'] == '2' || context['Tipo_richiedente3'] == '3' || context['Tipo_richiedente4'] == '4' || context['Tipo_richiedente5'] == '5' || context['Tipo_richiedente6'] == '6'",
                "description": {
                    "it": "Indicare il ruolo in virtù del quale si richiede l'accesso/consultazione agli atti."
                }
            },
            {
                "id": "block5",
                "type": "BLOCK",
                "name": {
                    "it": "Tipo di accesso richiesto"
                },
                "xpath": "(//*[contains(@class, 'simpatico-block')])[5]",
                "tags": [],
                "fields": [
                    "Tipo_richiedente1",
                    "Tipo_richiedente2",
                    "Tipo_richiedente3",
                    "Tipo_richiedente4",
                    "Tipo_richiedente5",
                    "Tipo_richiedente6",
                    "Servizio_richiesto1",
                    "Servizio_richiesto2"
                ],
                "blocks": [],
                "dependencies": [
                    "block4"
                ],
                "condition": "context['Tipo_richiedente1'] == '1' || context['Tipo_richiedente2'] == '2' || context['Tipo_richiedente3'] == '3' || context['Tipo_richiedente4'] == '4' || context['Tipo_richiedente5'] == '5' || context['Tipo_richiedente6'] == '6'",
                "completed": "context['Servizio_richiesto1'] == '1' || context['Servizio_richiesto2'] == '2'",
                "description": {
                    "it": "Indicare il tipo di richiesta: accesso, consultazione, oppure entrambe."
                }
            },
            {
                "id": "block6",
                "type": "BLOCK",
                "name": {
                    "it": "Documenti di interesse"
                },
                "xpath": "(//*[contains(@class, 'simpatico-block')])[6]",
                "tags": [],
                "fields": [
                    "Servizio_richiesto1",
                    "Servizio_richiesto2",
                    "atti_richiesti"
                ],
                "blocks": [],
                "dependencies": [
                    "block5"
                ],
                "condition": "context['Servizio_richiesto1'] == '1' || context['Servizio_richiesto2'] == '2'",
                "completed": "(context['atti_richiesti'] != null) && (context['atti_richiesti'] != '')",
                "description": {
                    "it": "Indicare gli atti/documenti per quali si richiede l'accesso/consultazione."
                }
            },
            {
                "id": "block7",
                "type": "BLOCK",
                "name": {
                    "it": "Motivazioni"
                },
                "xpath": "(//*[contains(@class, 'simpatico-block')])[7]",
                "tags": [],
                "fields": [
                    "atti_richiesti",
                    "Servizio_richiesto2"
                ],
                "blocks": [],
                "dependencies": [
                    "block6"
                ],
                "condition": "context['Servizio_richiesto2'] == '2' && (context['atti_richiesti'] != null) && (context['atti_richiesti'] != '')",
                "completed": null,
                "description": {
                    "it": "Indicare la motivazione per la quale si richiede l'accesso/consultazione agli atti di cui sopra."
                }
            },
            {
                "id": "block8",
                "type": "BLOCK",
                "name": {
                    "it": "Metodo ricezione"
                },
                "xpath": "(//*[contains(@class, 'simpatico-block')])[8]",
                "tags": [],
                "fields": [
                    "Metodo_ricezione1",
                    "Metodo_ricezione2",
                    "Metodo_ricezione3",
                    "Metodo_ricezione4",
                    "Metodo_ricezione5",
                    "Tipo_accesso4"
                ],
                "blocks": [],
                "dependencies": [
                    "block6"
                ],
                "condition": null,
                "completed": "context['Tipo_accesso4'] == '4' && (context['Metodo_ricezione1'] == '1' || context['Metodo_ricezione2'] == '2' || context['Metodo_ricezione3'] == '3' || context['Metodo_ricezione4'] == '4' || context['Metodo_ricezione5'] == '5')",
                "description": {
                    "it": "Indicare il metodo per la ricezione dei documenti richiesti."
                }
            },
            {
                "id": "block9",
                "type": "BLOCK",
                "name": {
                    "it": "Numero bollo"
                },
                "xpath": "(//*[contains(@class, 'simpatico-block')])[9]",
                "tags": [],
                "fields": [
                  "Metodo_ricezione1",
                  "Metodo_ricezione2",
                  "Metodo_ricezione3",
                  "Metodo_ricezione4",
                  "Metodo_ricezione5",
                  "Tipo_accesso4"
                ],
                "blocks": [],
                "dependencies": [
                  "block8"
                ],
                "condition": "context['Tipo_accesso4'] == '4' && (context['Metodo_ricezione1'] == '1' || context['Metodo_ricezione2'] == '2' || context['Metodo_ricezione3'] == '3' || context['Metodo_ricezione4'] == '4' || context['Metodo_ricezione5'] == '5')",
                "completed": null,
                "description": {
                    "it": "Inserire le 14 cifre del numero seriale della marca da bollo. Per ulteriori informazioni relative al pagamento dell'imposta di bollo si rimanda al link <i>“Come pagare?”</i> indicato nel modulo"
                }
            },
            {
                "id": "block10",
                "type": "BLOCK",
                "name": {
                    "it": "Allegati"
                },
                "xpath": "(//*[contains(@class, 'simpatico-block')])[10]",
                "tags": [],
                "fields": [],
                "blocks": [],
                "dependencies": [
                    "block9"
                ],
                "condition": null,
                "completed": null,
                "description": {
                    "it": "Indicare gli allegati necessari alla presentazione dell'istanza."
                }
            },
            {
                "id": "block11",
                "type": "BLOCK",
                "name": {
                    "it": "Informativa trattamento dati personali"
                },
                "xpath": "(//*[contains(@class, 'simpatico-block')])[11]",
                "tags": [],
                "fields": [
                    "Presa_visione_check"
                ],
                "blocks": [],
                "dependencies": [
                    "block10"
                ],
                "condition": null,
                "completed": "context['Presa_visione_check']=='1'",
                "description": {
                    "it": "Dichiarare di aver preso visione dell'informativa sulla privacy e il trattamento dei dati."
                }
            },
            {
                "id": "block12",
                "type": "BLOCK",
                "name": {
                    "it": "Conclusione della domanda"
                },
                "xpath": "(//*[contains(@class, 'simpatico-block')])[12]",
                "tags": [],
                "fields": [
                    "Presa_visione_check"
                ],
                "blocks": [],
                "dependencies": [
                    "block11"
                ],
                "condition": "context['Presa_visione_check']=='1'",
                "completed": null,
                "description": {
                    "it": "Termine presentazione della domanda. Per completare il modulo premere <i>“FINE”</i>. Verificare nuovamente tutti i dati inseriti e premere <b>“Salva modulo”</b>.  Verranno segnalate eventuali mancanze. In tal caso provvedere all’inserimento dei dati mancanti."
                }
            }
        ],
        "fields": [
            {
                "id": "AventeTitolo_CodiceFiscale",
                "xpath": "//*[@id=\"AventeTitolo_CodiceFiscale\"]",
                "mapping": {
                    "key": "AventeTitolo_CodiceFiscale",
                    "binding": "OUT"
                }
            },
            {
                "id": "Tipo_richiedente1",
                "xpath": "//*[@id=\"Tipo_richiedente1\"]",
                "mapping": {
                    "key": "Tipo_richiedente1",
                    "binding": "OUT"
                }
            },
            {
                "id": "Tipo_richiedente2",
                "xpath": "//*[@id=\"Tipo_richiedente2\"]",
                "mapping": {
                    "key": "Tipo_richiedente2",
                    "binding": "OUT"
                }
            },
            {
                "id": "Tipo_richiedente3",
                "xpath": "//*[@id=\"Tipo_richiedente3\"]",
                "mapping": {
                    "key": "Tipo_richiedente3",
                    "binding": "OUT"
                }
            },
            {
                "id": "Tipo_richiedente4",
                "xpath": "//*[@id=\"Tipo_richiedente4\"]",
                "mapping": {
                    "key": "Tipo_richiedente4",
                    "binding": "OUT"
                }
            },
            {
                "id": "Tipo_richiedente5",
                "xpath": "//*[@id=\"Tipo_richiedente5\"]",
                "mapping": {
                    "key": "Tipo_richiedente5",
                    "binding": "OUT"
                }
            },
            {
                "id": "Tipo_richiedente6",
                "xpath": "//*[@id=\"Tipo_richiedente6\"]",
                "mapping": {
                    "key": "Tipo_richiedente6",
                    "binding": "OUT"
                }
            },
            {
                "id": "Servizio_richiesto1",
                "xpath": "//*[@id=\"Servizio_richiesto1\"]",
                "mapping": {
                    "key": "Servizio_richiesto1",
                    "binding": "OUT"
                }
            },
            {
                "id": "Servizio_richiesto2",
                "xpath": "//*[@id=\"Servizio_richiesto2\"]",
                "mapping": {
                    "key": "Servizio_richiesto2",
                    "binding": "OUT"
                }
            },
            {
                "id": "atti_richiesti",
                "xpath": "//*[@id=\"atti_richiesti\"]",
                "mapping": {
                    "key": "atti_richiesti",
                    "binding": "OUT"
                }
            },
            {
                "id": "motivazione_richiesta",
                "xpath": "//*[@id=\"motivazione_richiesta\"]",
                "mapping": {
                    "key": "motivazione_richiesta",
                    "binding": "OUT"
                }
            },
            {
                "id": "Metodo_ricezione1",
                "xpath": "//*[@id=\"Metodo_ricezione1\"]",
                "mapping": {
                    "key": "Metodo_ricezione1",
                    "binding": "OUT"
                }
            },
            {
                "id": "Metodo_ricezione2",
                "xpath": "//*[@id=\"Metodo_ricezione2\"]",
                "mapping": {
                    "key": "Metodo_ricezione2",
                    "binding": "OUT"
                }
            },
            {
                "id": "Metodo_ricezione3",
                "xpath": "//*[@id=\"Metodo_ricezione3\"]",
                "mapping": {
                    "key": "Metodo_ricezione3",
                    "binding": "OUT"
                }
            },
            {
                "id": "Metodo_ricezione4",
                "xpath": "//*[@id=\"Metodo_ricezione4\"]",
                "mapping": {
                    "key": "Metodo_ricezione4",
                    "binding": "OUT"
                }
            },
            {
                "id": "Metodo_ricezione5",
                "xpath": "//*[@id=\"Metodo_ricezione5\"]",
                "mapping": {
                    "key": "Metodo_ricezione5",
                    "binding": "OUT"
                }
            },

            {
                "id": "Tipo_accesso4",
                "xpath": "//*[@id=\"Tipo_accesso4\"]",
                "mapping": {
                    "key": "Tipo_accesso4",
                    "binding": "OUT"
                }
            },
            {
                "id": "Presa_visione_check",
                "xpath": "//*[@id=\"Presa_visione_check\"]",
                "mapping": {
                    "key": "Presa_visione_check",
                    "binding": "OUT"
                }
            }
        ],
        "description": {
            "it": "Modulo per richiesta di accesso/consultazione atti in materia edilizia"
        },
        "name": {
            "it": "Richiesta accesso/consultazione atti in materia edilizia"
        },
        "workflow": [
            {
                "id": "step1",
                "name": {
                    "it": "Compilazione anagrafica richiedente"
                },
                "description": {
                    "it": "Compilare la parte anagrafica con i dati del richiedente e il ruolo a titolo del quale si richiede l'accesso o la consultazione."
                }
            },
            {
                "id": "step2",
                "name": {
                    "it": "Indicazione degli atti/documentazione e delle motivazioni"
                },
                "description": {
                    "it": "Specificare i documenti ai quali si richiede accesso/consultazione e le motivazioni della richiesta."
                }
            },
            {
                "id": "step3",
                "name": {
                    "it": "Metodo per la ricezione"
                },
                "description": {
                    "it": "Specificare il metodo preferenziale per l'accesso alla documentazione richiesta"
                }
            },
            {
                "id": "step4",
                "name": {
                    "it": "Marca da bollo, se richiesta"
                },
                "description": {
                    "it": "Dichiarare di aver annullato la marca da bollo, qualora richiesta, inserendo le 14 cifre del codice"
                }
            },
            {
                "id": "step5",
                "name": {
                    "it": "Allegati e informativa sul trattamento dei dati"
                },
                "description": {
                    "it": "Indicare tutta la documentazione allegata alla domanda e dichiarare di aver preso visione dell'informativa sul trattamento dei dati"
                }
            }
        ]
    }
}
