{
    "objectId": "be0acd9f-28fc-4f2f-b2ef-ea3582c27d6c",
    "creationDate": 1549535113963,
    "lastUpdate": 1549535113963,
    "uri": "https://sportello.comune.trento.it/modulistica/moduli/GEN-IMMAGG_vSTU3",
    "eserviceId": null,
    "profileTypes": [],
    "model": {
        "context": {},
        "blocks": [
            {
                "id": "block1",
                "type": "BLOCK",
                "name": {
                    "it": "Anagrafica del richiedente"
                },
                "xpath": "(//*[contains(@class, 'simpatico-block')])[1]",
                "tags": [],
                "fields": [
                    "Titolare_CodiceFiscale"
                ],
                "blocks": [],
                "dependencies": [],
                "condition": null,
                "completed": "(context['Titolare_CodiceFiscale'] != null) && (context['Titolare_CodiceFiscale'] != '')",
                "description": {
                    "it": "Dati recuperati automaticamente dal modulo principale. Verificarne la correttezza."
                }
            },
            {
                "id": "block2",
                "type": "BLOCK",
                "name": {
                    "it": "Ruolo del richiedente"
                },
                "xpath": "(//*[contains(@class, 'simpatico-block')])[2]",
                "tags": [],
                "fields": [
                    "Titolare_Ruolo"
                ],
                "blocks": [],
                "dependencies": [
                    "block1"
                ],
                "condition": "(context['Titolare_CodiceFiscale'] != null) && (context['Titolare_CodiceFiscale'] != '')",
                "completed": "context['Titolare_Ruolo'] != null",
                "description": {
                    "it": "Indicare il ruolo ricoperto dal richiedente nel contesto dei lavori da svolgere.<br>Dati recuperati automaticamente dal modulo principale. Verificarne la correttezza."
                }
            },
            {
                "id": "block3",
                "type": "BLOCK",
                "name": {
                    "it": "Ragione sociale del richiedente"
                },
                "xpath": "(//*[contains(@class, 'simpatico-block')])[3]",
                "tags": [],
                "fields": [
                    "Titolare_Ruolo"
                ],
                "blocks": [],
                "dependencies": [
                    "block2"
                ],
                "condition": "context['Titolare_Ruolo']=='Legale rappresentante'|| context['Titolare_Ruolo']=='Amministratore di condominio'",
                "completed": null,
                "description": {
                    "it": "Inserire i dati neccessari al fine di definire la ragione sociale/denominazione per conto della quale si sta eseguendo la richiesta."
                }
            },
            {
                "id": "block4",
                "type": "BLOCK",
                "name": {
                    "it": "Ulteriore particella catastale 1"
                },
                "xpath": "(//*[contains(@class, 'simpatico-block')])[4]",
                "tags": [],
                "fields": [],
                "blocks": [],
                "dependencies": [
                    "block2"
                ],
                "condition": null,
                "completed": null,
                "description": {
                    "it": "Inserire la prima particella o subalterno ulteriore, quindi verificarne l'esistenza premendo il pulsante <i>“Controllo particella”</i>.<br>Premere il pulsante <i>“Mappa”</i> per un controllo cartografico dei dati catastali immessi.<br><br>Le diciture <b>intero edificio</b> e <b>porzione di edificio</b> identificano la particella edificiale."
                }
            },
            {
                "id": "block5",
                "type": "BLOCK",
                "name": {
                    "it": "Ulteriore particella catastale 2"
                },
                "xpath": "(//*[contains(@class, 'simpatico-block')])[5]",
                "tags": [],
                "fields": [],
                "blocks": [],
                "dependencies": [
                    "block4"
                ],
                "condition": null,
                "completed": null,
                "description": {
                    "it": "Inserire la seconda particella o subalterno ulteriore, quindi verificarne l'esistenza premendo il pulsante <i>“Controllo particella”</i>.<br>Premere il pulsante <i>“Mappa”</i> per un controllo cartografico dei dati catastali immessi.<br><br>Le diciture <b>intero edificio</b> e <b>porzione di edificio</b> identificano la particella edificiale."
                }
            },
            {
                "id": "block6",
                "type": "BLOCK",
                "name": {
                    "it": "Ulteriore particella catastale 3"
                },
                "xpath": "(//*[contains(@class, 'simpatico-block')])[6]",
                "tags": [],
                "fields": [],
                "blocks": [],
                "dependencies": [
                    "block5"
                ],
                "condition": null,
                "completed": null,
                "description": {
                    "it": "Inserire la terza particella o subalterno ulteriore, quindi verificarne l'esistenza premendo il pulsante <i>“Controllo particella”</i>.<br>Premere il pulsante <i>“Mappa”</i> per un controllo cartografico dei dati catastali immessi.<br><br>Le diciture <b>intero edificio</b> e <b>porzione di edificio</b> identificano la particella edificiale."
                }
            },
            {
                "id": "block7",
                "type": "BLOCK",
                "name": {
                    "it": "Ulteriore particella catastale 4"
                },
                "xpath": "(//*[contains(@class, 'simpatico-block')])[7]",
                "tags": [],
                "fields": [],
                "blocks": [],
                "dependencies": [
                    "block6"
                ],
                "condition": null,
                "completed": null,
                "description": {
                    "it": "Inserire la quarta particella o subalterno ulteriore, quindi verificarne l'esistenza premendo il pulsante <i>“Controllo particella”</i>.<br>Premere il pulsante <i>“Mappa”</i> per un controllo cartografico dei dati catastali immessi.<br><br>Le diciture <b>intero edificio</b> e <b>porzione di edificio</b> identificano la particella edificiale."
                }
            },
            {
                "id": "block8",
                "type": "BLOCK",
                "name": {
                    "it": "Ulteriore particella catastale 5"
                },
                "xpath": "(//*[contains(@class, 'simpatico-block')])[8]",
                "tags": [],
                "fields": [],
                "blocks": [],
                "dependencies": [
                    "block7"
                ],
                "condition": null,
                "completed": null,
                "description": {
                    "it": "Inserire la quinta particella o subalterno ulteriore, quindi verificarne l'esistenza premendo il pulsante <i>“Controllo particella”</i>.<br>Premere il pulsante <i>“Mappa”</i> per un controllo cartografico dei dati catastali immessi.<br><br>Le diciture <b>intero edificio</b> e <b>porzione di edificio</b> identificano la particella edificiale."
                }
            },
            {
                "id": "block9",
                "type": "BLOCK",
                "name": {
                    "it": "Ulteriore particella catastale 6"
                },
                "xpath": "(//*[contains(@class, 'simpatico-block')])[9]",
                "tags": [],
                "fields": [],
                "blocks": [],
                "dependencies": [
                    "block8"
                ],
                "condition": null,
                "completed": null,
                "description": {
                    "it": "Inserire la sesta particella o subalterno ulteriore, quindi verificarne l'esistenza premendo il pulsante <i>“Controllo particella”</i>.<br>Premere il pulsante <i>“Mappa”</i> per un controllo cartografico dei dati catastali immessi.<br><br>Le diciture <b>intero edificio</b> e <b>porzione di edificio</b> identificano la particella edificiale."
                }
            },
            {
                "id": "block10",
                "type": "BLOCK",
                "name": {
                    "it": "Ulteriore particella catastale 7"
                },
                "xpath": "(//*[contains(@class, 'simpatico-block')])[10]",
                "tags": [],
                "fields": [],
                "blocks": [],
                "dependencies": [
                    "block9"
                ],
                "condition": null,
                "completed": null,
                "description": {
                    "it": "Inserire la settima particella o subalterno ulteriore, quindi verificarne l'esistenza premendo il pulsante <i>“Controllo particella”</i>.<br>Premere il pulsante <i>“Mappa”</i> per un controllo cartografico dei dati catastali immessi.<br><br>Le diciture <b>intero edificio</b> e <b>porzione di edificio</b> identificano la particella edificiale."
                }
            },
            {
                "id": "block11",
                "type": "BLOCK",
                "name": {
                    "it": "Ulteriore particella catastale 8"
                },
                "xpath": "(//*[contains(@class, 'simpatico-block')])[11]",
                "tags": [],
                "fields": [],
                "blocks": [],
                "dependencies": [
                    "block10"
                ],
                "condition": null,
                "completed": null,
                "description": {
                    "it": "Inserire l'ottava particella o subalterno ulteriore, quindi verificarne l'esistenza premendo il pulsante <i>“Controllo particella”</i>.<br>Premere il pulsante <i>“Mappa”</i> per un controllo cartografico dei dati catastali immessi.<br><br>Le diciture <b>intero edificio</b> e <b>porzione di edificio</b> identificano la particella edificiale."
                }
            },
            {
                "id": "block12",
                "type": "BLOCK",
                "name": {
                    "it": "Ulteriore particella catastale 9"
                },
                "xpath": "(//*[contains(@class, 'simpatico-block')])[12]",
                "tags": [],
                "fields": [],
                "blocks": [],
                "dependencies": [
                    "block11"
                ],
                "condition": null,
                "completed": null,
                "description": {
                    "it": "Inserire la nona particella o subalterno ulteriore, quindi verificarne l'esistenza premendo il pulsante <i>“Controllo particella”</i>.<br>Premere il pulsante <i>“Mappa”</i> per un controllo cartografico dei dati catastali immessi.<br><br>Le diciture <b>intero edificio</b> e <b>porzione di edificio</b> identificano la particella edificiale."
                }
            },
            {
                "id": "block13",
                "type": "BLOCK",
                "name": {
                    "it": "Ulteriore particella catastale 10"
                },
                "xpath": "(//*[contains(@class, 'simpatico-block')])[13]",
                "tags": [],
                "fields": [],
                "blocks": [],
                "dependencies": [
                    "block12"
                ],
                "condition": null,
                "completed": null,
                "description": {
                    "it": "Inserire la decima particella o subalterno ulteriore, quindi verificarne l'esistenza premendo il pulsante <i>“Controllo particella”</i>.<br>Premere il pulsante <i>“Mappa”</i> per un controllo cartografico dei dati catastali immessi.<br><br>Le diciture <b>intero edificio</b> e <b>porzione di edificio</b> identificano la particella edificiale."
                }
            },
            {
                "id": "block14",
                "type": "BLOCK",
                "name": {
                    "it": "Conclusione della domanda"
                },
                "xpath": "//*[@id='firme']",
                "tags": [],
                "fields": [],
                "blocks": [],
                "dependencies": [
                    "block13"
                ],
                "condition": null,
                "completed": null,
                "description": {
                    "it": "Termine modulo secondario: specificare luogo e data. Per completare il modulo premere <i>“FINE”</i>. Verificare nuovamente tutti i dati inseriti e premere <b>“Salva modulo”</b>.  Verranno segnalate eventuali mancanze. In tal caso provvedere all’inserimento dei dati mancanti."
                }
            }
        ],
        "fields": [
            {
                "id": "Titolare_CodiceFiscale",
                "xpath": "//*[@id=\"Titolare_CodiceFiscale\"]",
                "mapping": {
                    "key": "Titolare_CodiceFiscale",
                    "binding": "OUT"
                }
            },
            {
                "id": "Titolare_Ruolo",
                "xpath": "//*[@id=\"Titolare_Ruolo\"]",
                "mapping": {
                    "key": "Titolare_Ruolo",
                    "binding": "OUT"
                }
            }
        ],
        "description": {
            "it": "Modulo per la definizione delle ulteriori particelle catastali coinvolte"
        },
        "name": {
            "it": "Ulteriori particelle"
        },
        "workflow": [
            {
                "id": "step1",
                "name": {
                    "it": "Verifica anagrafica del richiedente"
                },
                "description": {
                    "it": "Verificare la correttezza dei dati del richiedente recuperati dall'istanza' di riferimento"
                }
            },
            {
                "id": "step2",
                "name": {
                    "it": "Elenco ulteriori particelle catastali"
                },
                "description": {
                    "it": "Indicare le ulteriori particelle catastali oggetto dell'istanza"
                }
            }
        ]
    }
}
