{
    "objectId": "6ed4d214-686d-4b66-81bb-3dc2d75192a9",
    "creationDate": 1553770759057,
    "lastUpdate": 1553770759057,
    "uri": "https://sportello.comune.trento.it/modulistica/moduli/M1145-DISPONIBILITA-PRESIDENTE-SEGGIO_vSTU3",
    "eserviceId": null,
    "profileTypes": [],
    "model": {
        "context": {},
        "blocks": [
          {
              "id": "block1",
              "type": "BLOCK",
              "name": {
                  "it": "Caricamento dati del richiedente"
              },
              "xpath": "(//*[contains(@class, 'simpatico-block')])[1]",
              "tags": [],
              "fields": [
                  "AventeTitolo_CodiceFiscale"
              ],
              "blocks": [],
              "dependencies": [],
              "condition": null,
              "completed": "context['AventeTitolo_CodiceFiscale'] != null && context['AventeTitolo_CodiceFiscale'] != ''",
              "annotations": [],
              "description": {
                  "it": "Una volta effettuato l’accesso con la carta dei servizi o con SPID, premere l'icona nera a forma di omino oppure digitare il proprio codice fiscale nel campo appostito; quindi premere il pulsante <i>“Carica dati anagrafici”</i> per recuperare automaticamente le informazioni anagrafiche.<br><br>Premere il pulsante <i>“SUCCESSIVO”</i> per proseguire la compilazione."
              },
              "concepts": null
          },
          {
              "id": "block2",
              "type": "BLOCK",
              "name": {
                  "it": "Anagrafica del richiedente"
              },
              "xpath": "(//*[contains(@class, 'simpatico-block')])[2]",
              "tags": [],
              "fields": [
                  "AventeTitolo_CodiceFiscale",
                  "AventeTitolo_Cittadinanza"
              ],
              "blocks": [],
              "dependencies": [
                "block1"
              ],
              "condition": "context['AventeTitolo_CodiceFiscale'] != null && context['AventeTitolo_CodiceFiscale'] != ''",
              "completed": "context['AventeTitolo_Cittadinanza'] == 'ITALIANA' || context['AventeTitolo_Cittadinanza'] == 'Italiana' || context['AventeTitolo_Cittadinanza'] == 'italiana'",
              "annotations": [],
              "description": {
                  "it": "Verificare i dati caricati automaticamente.<br>NOTA: Se il richiedente non risiede nell'Unione Europea, selezionare come provincia di residenza l'opzione <i>“EE”</i> e inserire la nazione di residenza nel campo “Indirizzo”.<br><br><b>IMPORTANTE! La domanda può essere presentata solo da richiedenti aventi cittadinanza Italiana</b><br><br><b>ATTENZIONE! I campi evidenziati in arancione sono obbligatori.</b>"
              },
              "concepts": null
          },
          {
              "id": "block3",
              "type": "BLOCK",
              "name": {
                  "it": "Dati di residenza del richiedente"
              },
              "xpath": "(//*[contains(@class, 'simpatico-block')])[3]",
              "tags": [],
              "fields": [
                  "AventeTitolo_Cittadinanza",
                  "AventeTitolo_ComuneResidenza"
              ],
              "blocks": [],
              "dependencies": [
                "block2"
              ],
              "condition": "context['AventeTitolo_Cittadinanza'] == 'ITALIANA' || context['AventeTitolo_Cittadinanza'] == 'Italiana' || context['AventeTitolo_Cittadinanza'] == 'italiana'",
              "completed": "context['AventeTitolo_ComuneResidenza'] == 'TRENTO' || context['AventeTitolo_ComuneResidenza'] == 'Trento' || context['AventeTitolo_ComuneResidenza'] == 'trento'",
              "annotations": [],
              "description": {
                  "it": "Sono qui riportate le informazioni relative alla residenza del richiedente, in caso di informazioni mancanti tornare al blocco iniziale e premere nuovamente <i>“Carica dati anagrafici”</i>.<br><br><b>IMPORTANTE! La domanda può essere presentata solo da richiedenti residenti a Trento</b>"
              },
              "concepts": null
          },
          {
              "id": "block4",
              "type": "BLOCK",
              "name": {
                  "it": "Situazione lavorativa del richiedente"
              },
              "xpath": "(//*[contains(@class, 'simpatico-block')])[4]",
              "tags": [],
              "fields": [
                  "AventeTitolo_ComuneResidenza",
                  "Lavoro_richiedente1",
                  "Lavoro_richiedente2",
                  "Lavoro_richiedente3",
                  "Lavoro_richiedente4"
              ],
              "blocks": [],
              "dependencies": [
                  "block3"
              ],
              "condition": "context['AventeTitolo_ComuneResidenza'] == 'TRENTO' || context['AventeTitolo_ComuneResidenza'] == 'Trento' || context['AventeTitolo_ComuneResidenza'] == 'trento'",
              "completed": "context['Lavoro_richiedente1']=='Lavoratore' || context['Lavoro_richiedente2']=='Studente' || context['Lavoro_richiedente3']=='Studente/Lavoratore' || context['Lavoro_richiedente4']=='Non occupato/Pensionato'",
              "annotations": [],
              "description": {
                  "it": "Indicare la situazione lavorativa del richiedente.<br><br><b>NB: è obbligatoria la scelta di una delle opzioni."
              },
              "concepts": null
          },
          {
              "id": "block5",
              "type": "BLOCK",
              "name": {
                  "it": "Dichiarazione iscrizione all'albo"
              },
              "xpath": "(//*[contains(@class, 'simpatico-block')])[5]",
              "tags": [],
              "fields": [
                  "Lavoro_richiedente1",
                  "Lavoro_richiedente2",
                  "Lavoro_richiedente3",
                  "Lavoro_richiedente4",
                  "Iscrizione_albo1",
                  "Data_iscrizione_albo1"
              ],
              "blocks": [],
              "dependencies": [
                  "block4"
              ],
              "condition": "context['Lavoro_richiedente1']=='Lavoratore' || context['Lavoro_richiedente2']=='Studente' || context['Lavoro_richiedente3']=='Studente/Lavoratore' || context['Lavoro_richiedente4']=='Non occupato/Pensionato'",
              "completed": "context['Iscrizione_albo1']=='Iscritto albo' && context['Data_iscrizione_albo1']=='Iscritto entro termine ultimo'",
              "annotations": [],
              "description": {
                  "it": "Indicare se il richiedente è iscritto all'albo dei presidenti e in caso affermativo se l'iscrizione è avvenuta entro i termini indicati<br><br><b>NB: è obbligatoria la scelta di una delle opzioni.<br><br><b>IMPORTANTE! Condizione di ammissibilità della domanda è che l'iscrizione all'albo dei presidenti sia avvenuta entro il 31 ottobre 2018.</b><br>Qualora l'iscrizione fosse successiva a tale data non sarà possibile inviare il modulo.<br>In questo caso gli interessati possono contattare telefonicamente l'Ufficio Elettorale, ai numeri 0461-884299 o 0461884298, per dare disponibilità alla sostituzione in caso di necessità."
              },
              "concepts": null
          },
          {
              "id": "block6",
              "type": "BLOCK",
              "name": {
                  "it": "Informazioni impegno richiesto"
              },
              "xpath": "(//*[contains(@class, 'simpatico-block')])[6]",
              "tags": [],
              "fields": [
                  "Iscrizione_albo1",
                  "Data_iscrizione_albo1"
              ],
              "blocks": [],
              "dependencies": [
                  "block5"
              ],
              "condition": "context['Iscrizione_albo1']=='Iscritto albo' && context['Data_iscrizione_albo1']=='Iscritto entro termine ultimo'",
              "completed": null,
              "annotations": [],
              "description": {
                  "it": "Leggere le informazioni relative all'impegno che il ruolo di presidente di seggio comporta"
              },
              "concepts": null
          },
            {
                "id": "block7",
                "type": "BLOCK",
                "name": {
                    "it": "Incarichi precedenti"
                },
                "xpath": "(//*[contains(@class, 'simpatico-block')])[7]",
                "tags": [],
                "fields": [
                    "ruolo_pres1",
                    "ruolo_pres2",
                    "ruolo_scrut1",
                    "ruolo_scrut2",
                    "ruolo_segr1",
                    "ruolo_segr2"
                ],
                "blocks": [],
                "dependencies": [
                    "block6"
                ],
                "condition": null,
                "completed": "(context['ruolo_pres1'] == 'già presidente' || context['ruolo_pres2'] == 'mai presidente') && (context['ruolo_scrut1'] == 'già scrutatore' || context['ruolo_scrut2'] == 'mai scrutatore') && (context['ruolo_segr1'] == 'già segretario' || context['ruolo_segr2'] == 'mai segretario')",
                "annotations": [],
                "description": {
                    "it": "Indicare se il richiedente ha svolto il ruolo di presidente/scrutatore/segretario in precedenti tornate elettorali."
                },
                "concepts": null
            },
            {
                "id": "block8",
                "type": "BLOCK",
                "name": {
                    "it": "Verifica ammissibilità domanda"
                },
                "xpath": "(//*[contains(@class, 'simpatico-block')])[8]",
                "tags": [],
                "fields": [
                    "ruolo_pres1",
                    "ruolo_pres2",
                    "ruolo_scrut1",
                    "ruolo_scrut2",
                    "ruolo_segr1",
                    "ruolo_segr2"
                ],
                "blocks": [],
                "dependencies": [
                    "block7"
                ],
                "condition": "(context['ruolo_pres1'] == 'già presidente' || context['ruolo_pres2'] == 'mai presidente') && (context['ruolo_scrut1'] == 'già scrutatore' || context['ruolo_scrut2'] == 'mai scrutatore') && (context['ruolo_segr1'] == 'già segretario' || context['ruolo_segr2'] == 'mai segretario')",
                "completed": null,
                "annotations": [],
                "description": {
                    "it": "Verifica dell'ammissibilità della domanda: se tutte le voci sono spuntate sarà possibile inviare l'istanza."
                },
                "concepts": null
            },
            {
                "id": "block9",
                "type": "BLOCK",
                "name": {
                    "it": "Indicazione IBAN per accredito compenso"
                },
                "xpath": "(//*[contains(@class, 'simpatico-block')])[9]",
                "tags": [],
                "fields": [],
                "blocks": [],
                "dependencies": [
                    "block8"
                ],
                "condition": null,
                "completed": null,
                "annotations": [],
                "description": {
                    "it": "Il richiedente, se intestatario o cointestatario di conto corrente, può indicare le coordinate per l'accredito del compenso qualora svolga l'incarico di scrutatore."
                },
                "concepts": null
            },
            {
                "id": "block10",
                "type": "BLOCK",
                "name": {
                    "it": "Informativa trattamento dati personali"
                },
                "xpath": "(//*[contains(@class, 'simpatico-block')])[10]",
                "tags": [],
                "fields": [
                    "Presa_visione_check"
                ],
                "blocks": [],
                "dependencies": [
                    "block9"
                ],
                "condition": null,
                "completed": "context['Presa_visione_check'] =='1'",
                "annotations": [],
                "description": {
                    "it": "Dichiarare di aver preso visione dell'informativa sul trattamento dei dati personali"
                },
                "concepts": null
            },
            {
                "id": "block11",
                "type": "BLOCK",
                "name": {
                    "it": "Conclusione della domanda"
                },
                "xpath": "//*[@id='firme']",
                "tags": [],
                "fields": [
                    "Presa_visione_check"
                ],
                "blocks": [],
                "dependencies": [
                    "block10"
                ],
                "condition": "context['Presa_visione_check'] =='1'",
                "completed": null,
                "annotations": [],
                "description": {
                    "it": "Termine presentazione della domanda: specificare luogo e data. Per completare il modulo premere <i>“FINE”</i>. Verificare nuovamente tutti i dati inseriti e premere <b>“Salva modulo”</b>.  Verranno segnalate eventuali mancanze. In tal caso provvedere all’inserimento dei dati mancanti."
                },
                "concepts": null
            }
        ],
        "fields": [
            {
                "id": "AventeTitolo_CodiceFiscale",
                "xpath": "//*[@id=\"AventeTitolo_CodiceFiscale\"]",
                "mapping": {
                    "key": "AventeTitolo_CodiceFiscale",
                    "binding": "OUT"
                }
            },
            {
                "id": "AventeTitolo_Cittadinanza",
                "xpath": "//*[@id=\"AventeTitolo_Cittadinanza\"]",
                "mapping": {
                    "key": "AventeTitolo_Cittadinanza",
                    "binding": "OUT"
                }
            },
            {
                "id": "AventeTitolo_ComuneResidenza",
                "xpath": "//*[@id=\"AventeTitolo_ComuneResidenza\"]",
                "mapping": {
                    "key": "AventeTitolo_ComuneResidenza",
                    "binding": "OUT"
                }
            },
            {
                "id": "Lavoro_richiedente1",
                "xpath": "//*[@id=\"Lavoro_richiedente1\"]",
                "mapping": {
                    "key": "Lavoro_richiedente1",
                    "binding": "OUT"
                }
            },
            {
                "id": "Lavoro_richiedente2",
                "xpath": "//*[@id=\"Lavoro_richiedente2\"]",
                "mapping": {
                    "key": "Lavoro_richiedente2",
                    "binding": "OUT"
                }
            },
            {
                "id": "Lavoro_richiedente3",
                "xpath": "//*[@id=\"Lavoro_richiedente3\"]",
                "mapping": {
                    "key": "Lavoro_richiedente3",
                    "binding": "OUT"
                }
            },
            {
                "id": "Lavoro_richiedente4",
                "xpath": "//*[@id=\"Lavoro_richiedente4\"]",
                "mapping": {
                    "key": "Lavoro_richiedente4",
                    "binding": "OUT"
                }
            },
            {
                "id": "Iscrizione_albo1",
                "xpath": "//*[@id=\"Iscrizione_albo1\"]",
                "mapping": {
                    "key": "Iscrizione_albo1",
                    "binding": "OUT"
                }
            },
            {
                "id": "Data_iscrizione_albo1",
                "xpath": "//*[@id=\"Data_iscrizione_albo1\"]",
                "mapping": {
                    "key": "Data_iscrizione_albo1",
                    "binding": "OUT"
                }
            },
            {
                "id": "Data_iscrizione_albo1",
                "xpath": "//*[@id=\"Data_iscrizione_albo1\"]",
                "mapping": {
                    "key": "Data_iscrizione_albo1",
                    "binding": "OUT"
                }
            },
            {
                "id": "Data_iscrizione_albo1",
                "xpath": "//*[@id=\"Data_iscrizione_albo1\"]",
                "mapping": {
                    "key": "Data_iscrizione_albo1",
                    "binding": "OUT"
                }
            },
            {
                "id": "ruolo_pres1",
                "xpath": "//*[@id=\"ruolo_pres1\"]",
                "mapping": {
                    "key": "ruolo_pres1",
                    "binding": "OUT"
                }
            },
            {
                "id": "ruolo_pres2",
                "xpath": "//*[@id=\"ruolo_pres2\"]",
                "mapping": {
                    "key": "ruolo_pres2",
                    "binding": "OUT"
                }
            },
            {
                "id": "ruolo_scrut1",
                "xpath": "//*[@id=\"ruolo_scrut1\"]",
                "mapping": {
                    "key": "ruolo_scrut1",
                    "binding": "OUT"
                }
            },
            {
                "id": "ruolo_scrut2",
                "xpath": "//*[@id=\"ruolo_scrut2\"]",
                "mapping": {
                    "key": "ruolo_scrut2",
                    "binding": "OUT"
                }
            },
            {
                "id": "ruolo_segr1",
                "xpath": "//*[@id=\"ruolo_segr1\"]",
                "mapping": {
                    "key": "ruolo_segr1",
                    "binding": "OUT"
                }
            },
            {
                "id": "ruolo_segr2",
                "xpath": "//*[@id=\"ruolo_segr2\"]",
                "mapping": {
                    "key": "ruolo_segr2",
                    "binding": "OUT"
                }
            },
            {
                "id": "Presa_visione_check",
                "xpath": "//*[@id=\"Presa_visione_check\"]",
                "mapping": {
                    "key": "Presa_visione_check",
                    "binding": "OUT"
                }
            }
        ],
        "services": [],
        "questions": [],
        "description": {
            "it": "Modulo dichiarazione disponibilità a svolgere il ruolo di scrutatore di seggio elettorale"
        },
        "name": {
            "it": "Dichiarzione di disponibilità a svolgere il ruolo di scrutatore di seggio elettorale"
        },
        "workflow": [
            {
                "id": "step1",
                "name": {
                    "it": "Compilazione anagrafica"
                },
                "description": {
                    "it": "Il richiedente deve inserire i propri dati anagrafici (recuperati in automatico mediante l'apposito pulsante)."
                }
            },
            {
                "id": "step2",
                "name": {
                    "it": "Dichiarazione condizione lavorativa e stato di iscrizione all'albo"
                },
                "description": {
                    "it": "Il richiedente deve indicare la propria condizione lavorativa, quindi lo stato di iscrizione all'albo degli scrutatori e la data di iscrizione."
                }
            },
            {
                "id": "step3",
                "name": {
                    "it": "Dichiarazione disponibilità"
                },
                "description": {
                    "it": "Leggere le informazioni relative all'impegno che il ruolo di scrutatore comporta."
                }
            },
            {
                "id": "step4",
                "name": {
                    "it": "Dichiarazione ruoli precedenti"
                },
                "description": {
                    "it": "Il richiedente deve indicare se ha già ricoperto il ruolo di presidente/scrutatore/segretario in una delle precedenti tornate elettorali."
                }
            },
            {
                "id": "step5",
                "name": {
                    "it": "Indicazione IBAN per accredito"
                },
                "description": {
                    "it": "Il richiedente può indicare l'IBAN sul quale, qualora svolga l'incarico di scrutatore, verrà accreditato il compenso economico."
                }
            },
            {
                "id": "step6",
                "name": {
                    "it": "Dichiarazioni finali e accettazione trattamento dei dati"
                },
                "description": {
                    "it": "Dichiarazioni conclusive obbligatorie e presa visione e accettazione del trattamento dei dati personali inseriti nel modulo."
                }
            }
        ]
    }
}
